instrumentlab/__init__.py
instrumentlab/agilent/__init__.py
instrumentlab/agilent/dso54830b.py
instrumentlab/agilent/dso54830b_xx.py
instrumentlab/agilent/infiniium/__init__.py
instrumentlab/agilent/infiniium/infiniium_channel.py
instrumentlab/agilent/infiniium/infiniium_scope.py
instrumentlab/base/attribute.py
instrumentlab/base/config.py
instrumentlab/base/instrument.py
instrumentlab/base/link_base.py
instrumentlab/base/subsystem.py
instrumentlab/base/oscilloscope/oscillocope_constants.py
instrumentlab/base/oscilloscope/oscilloscope.py
instrumentlab/base/oscilloscope/oscilloscope_channel.py
instrumentlab/base/psu/simple_psu.py
instrumentlab/ea/__init__.py
instrumentlab/ea/ea_psi9000.py
instrumentlab/korad/__init__.py
instrumentlab/korad/kaxxxxp.py
instrumentlab/korad/korad_slow_serial.py
instrumentlab/links/__init__.py
instrumentlab/links/visa/pyvisa_link.py
instrumentlab/links/visa/visa_factory.py
instrumentlab/velleman/__init__.py
instrumentlab/velleman/labps3005d.py
instrumentlab/velleman/labps3005dn.py
instrumentlab-0.0.5.dist-info/LICENSE
instrumentlab-0.0.5.dist-info/METADATA
instrumentlab-0.0.5.dist-info/NOTICE
instrumentlab-0.0.5.dist-info/WHEEL
instrumentlab-0.0.5.dist-info/top_level.txt
instrumentlab-0.0.5.dist-info/RECORD
