Metadata-Version: 2.1
Name: instrumentlab
Version: 0.0.5
Summary: Controlling test instruments like oscilloscopes, power supplies, ...
License: Apache-2.0
Project-URL: Homepage, https://github.com/mvanriet/instrumentlab
Project-URL: Documentation, https://github.com/mvanriet/instrumentlab/wiki
Requires-Python: >=3.5
License-File: LICENSE
License-File: NOTICE
